opencerebro/tools/embed_sci/__init__.py
opencerebro_tool_embed_sci-0.1.2.dist-info/METADATA
opencerebro_tool_embed_sci-0.1.2.dist-info/WHEEL
opencerebro_tool_embed_sci-0.1.2.dist-info/RECORD
